{
  "bg": 207, 
  "temp": "absolute", 
  "snoozeBG": 201, 
  "timestamp": "2016-06-24T22:41:17.599093", 
  "missing": [
    "duration", 
    "rate"
  ], 
  "reason": "Eventual BG 201>=175, temp 2.125 >~ req 2.17U/hr", 
  "eventualBG": 201, 
  "error": "missing required input fields", 
  "input": {
    "reason": "Eventual BG 201>=175, temp 2.125 >~ req 2.17U/hr", 
    "bg": 207, 
    "eventualBG": 201, 
    "temp": "absolute", 
    "snoozeBG": 201, 
    "mealAssist": "Off: Carbs: 0 Boluses: 1.7 ISF: 36, Target: 143 Deviation: -6 BGI: 0", 
    "tick": "+0"
  }, 
  "mealAssist": "Off: Carbs: 0 Boluses: 1.7 ISF: 36, Target: 143 Deviation: -6 BGI: 0", 
  "tick": "+0"
}