[
  {
    "duration": "30",
    "raw_duration": {
      "_type": "TempBasalDuration",
      "_description": "TempBasalDuration 2016-07-08T03:31:11 head[2], body[0] op[0x16]",
      "timestamp": "2016-07-08T03:31:11-04:00",
      "_body": "",
      "_head": "1601",
      "duration (min)": 30,
      "_date": "4bdf034810"
    },
    "timestamp": "2016-07-08T03:31:11-04:00",
    "absolute": "1.6",
    "rate": 1.6,
    "raw_rate": {
      "_type": "TempBasal",
      "temp": "absolute",
      "_description": "TempBasal 2016-07-08T03:31:11 head[2], body[1] op[0x33]",
      "timestamp": "2016-07-08T03:31:11-04:00",
      "_body": "00",
      "_head": "3340",
      "rate": 1.6,
      "_date": "4bdf034810"
    },
    "eventType": "Temp Basal",
    "medtronic": "mm://openaps/mm-format-ns-treatments/Temp Basal",
    "created_at": "2016-07-08T03:31:11-04:00",
    "enteredBy": "openaps://medtronic/722"
  },
  {
    "duration": "30",
    "raw_duration": {
      "_type": "TempBasalDuration",
      "_description": "TempBasalDuration 2016-07-08T03:26:01 head[2], body[0] op[0x16]",
      "timestamp": "2016-07-08T03:26:01-04:00",
      "_body": "",
      "_head": "1601",
      "duration (min)": 30,
      "_date": "41da034810"
    },
    "timestamp": "2016-07-08T03:26:01-04:00",
    "absolute": "0.75",
    "rate": 0.75,
    "raw_rate": {
      "_type": "TempBasal",
      "temp": "absolute",
      "_description": "TempBasal 2016-07-08T03:26:01 head[2], body[1] op[0x33]",
      "timestamp": "2016-07-08T03:26:01-04:00",
      "_body": "00",
      "_head": "331e",
      "rate": 0.75,
      "_date": "41da034810"
    },
    "eventType": "Temp Basal",
    "medtronic": "mm://openaps/mm-format-ns-treatments/Temp Basal",
    "created_at": "2016-07-08T03:26:01-04:00",
    "enteredBy": "openaps://medtronic/722"
  },
  {
    "duration": "30",
    "raw_duration": {
      "_type": "TempBasalDuration",
      "_description": "TempBasalDuration 2016-07-08T03:16:01 head[2], body[0] op[0x16]",
      "timestamp": "2016-07-08T03:16:01-04:00",
      "_body": "",
      "_head": "1601",
      "duration (min)": 30,
      "_date": "41d0034810"
    },
    "timestamp": "2016-07-08T03:16:01-04:00",
    "absolute": "0",
    "rate": 0,
    "raw_rate": {
      "_type": "TempBasal",
      "temp": "absolute",
      "_description": "TempBasal 2016-07-08T03:16:01 head[2], body[1] op[0x33]",
      "timestamp": "2016-07-08T03:16:01-04:00",
      "_body": "00",
      "_head": "3300",
      "rate": 0,
      "_date": "41d0034810"
    },
    "eventType": "Temp Basal",
    "medtronic": "mm://openaps/mm-format-ns-treatments/Temp Basal",
    "created_at": "2016-07-08T03:16:01-04:00",
    "enteredBy": "openaps://medtronic/722"
  },
  {
    "duration": "30",
    "raw_duration": {
      "_type": "TempBasalDuration",
      "_description": "TempBasalDuration 2016-07-08T03:01:09 head[2], body[0] op[0x16]",
      "timestamp": "2016-07-08T03:01:09-04:00",
      "_body": "",
      "_head": "1601",
      "duration (min)": 30,
      "_date": "49c1034810"
    },
    "timestamp": "2016-07-08T03:01:09-04:00",
    "absolute": "0",
    "rate": 0,
    "raw_rate": {
      "_type": "TempBasal",
      "temp": "absolute",
      "_description": "TempBasal 2016-07-08T03:01:09 head[2], body[1] op[0x33]",
      "timestamp": "2016-07-08T03:01:09-04:00",
      "_body": "00",
      "_head": "3300",
      "rate": 0,
      "_date": "49c1034810"
    },
    "eventType": "Temp Basal",
    "medtronic": "mm://openaps/mm-format-ns-treatments/Temp Basal",
    "created_at": "2016-07-08T03:01:09-04:00",
    "enteredBy": "openaps://medtronic/722"
  },
  {
    "duration": "30",
    "raw_duration": {
      "_type": "TempBasalDuration",
      "_description": "TempBasalDuration 2016-07-08T02:46:00 head[2], body[0] op[0x16]",
      "timestamp": "2016-07-08T02:46:00-04:00",
      "_body": "",
      "_head": "1601",
      "duration (min)": 30,
      "_date": "40ee024810"
    },
    "timestamp": "2016-07-08T02:46:00-04:00",
    "absolute": "0.75",
    "rate": 0.75,
    "raw_rate": {
      "_type": "TempBasal",
      "temp": "absolute",
      "_description": "TempBasal 2016-07-08T02:46:00 head[2], body[1] op[0x33]",
      "timestamp": "2016-07-08T02:46:00-04:00",
      "_body": "00",
      "_head": "331e",
      "rate": 0.75,
      "_date": "40ee024810"
    },
    "eventType": "Temp Basal",
    "medtronic": "mm://openaps/mm-format-ns-treatments/Temp Basal",
    "created_at": "2016-07-08T02:46:00-04:00",
    "enteredBy": "openaps://medtronic/722"
  },
  {
    "duration": "30",
    "raw_duration": {
      "_type": "TempBasalDuration",
      "_description": "TempBasalDuration 2016-07-08T02:21:11 head[2], body[0] op[0x16]",
      "timestamp": "2016-07-08T02:21:11-04:00",
      "_body": "",
      "_head": "1601",
      "duration (min)": 30,
      "_date": "4bd5024810"
    },
    "timestamp": "2016-07-08T02:21:11-04:00",
    "absolute": "0",
    "rate": 0,
    "raw_rate": {
      "_type": "TempBasal",
      "temp": "absolute",
      "_description": "TempBasal 2016-07-08T02:21:11 head[2], body[1] op[0x33]",
      "timestamp": "2016-07-08T02:21:11-04:00",
      "_body": "00",
      "_head": "3300",
      "rate": 0,
      "_date": "4bd5024810"
    },
    "eventType": "Temp Basal",
    "medtronic": "mm://openaps/mm-format-ns-treatments/Temp Basal",
    "created_at": "2016-07-08T02:21:11-04:00",
    "enteredBy": "openaps://medtronic/722"
  },
  {
    "duration": "30",
    "raw_duration": {
      "_type": "TempBasalDuration",
      "_description": "TempBasalDuration 2016-07-08T02:16:05 head[2], body[0] op[0x16]",
      "timestamp": "2016-07-08T02:16:05-04:00",
      "_body": "",
      "_head": "1601",
      "duration (min)": 30,
      "_date": "45d0024810"
    },
    "timestamp": "2016-07-08T02:16:05-04:00",
    "absolute": "0.75",
    "rate": 0.75,
    "raw_rate": {
      "_type": "TempBasal",
      "temp": "absolute",
      "_description": "TempBasal 2016-07-08T02:16:05 head[2], body[1] op[0x33]",
      "timestamp": "2016-07-08T02:16:05-04:00",
      "_body": "00",
      "_head": "331e",
      "rate": 0.75,
      "_date": "45d0024810"
    },
    "eventType": "Temp Basal",
    "medtronic": "mm://openaps/mm-format-ns-treatments/Temp Basal",
    "created_at": "2016-07-08T02:16:05-04:00",
    "enteredBy": "openaps://medtronic/722"
  },
  {
    "duration": "30",
    "raw_duration": {
      "_type": "TempBasalDuration",
      "_description": "TempBasalDuration 2016-07-08T02:10:55 head[2], body[0] op[0x16]",
      "timestamp": "2016-07-08T02:10:55-04:00",
      "_body": "",
      "_head": "1601",
      "duration (min)": 30,
      "_date": "77ca024810"
    },
    "timestamp": "2016-07-08T02:10:55-04:00",
    "absolute": "0",
    "rate": 0,
    "raw_rate": {
      "_type": "TempBasal",
      "temp": "absolute",
      "_description": "TempBasal 2016-07-08T02:10:55 head[2], body[1] op[0x33]",
      "timestamp": "2016-07-08T02:10:55-04:00",
      "_body": "00",
      "_head": "3300",
      "rate": 0,
      "_date": "77ca024810"
    },
    "eventType": "Temp Basal",
    "medtronic": "mm://openaps/mm-format-ns-treatments/Temp Basal",
    "created_at": "2016-07-08T02:10:55-04:00",
    "enteredBy": "openaps://medtronic/722"
  },
  {
    "duration": "30",
    "raw_duration": {
      "_type": "TempBasalDuration",
      "_description": "TempBasalDuration 2016-07-08T01:51:03 head[2], body[0] op[0x16]",
      "timestamp": "2016-07-08T01:51:03-04:00",
      "_body": "",
      "_head": "1601",
      "duration (min)": 30,
      "_date": "43f3014810"
    },
    "timestamp": "2016-07-08T01:51:03-04:00",
    "absolute": "0",
    "rate": 0,
    "raw_rate": {
      "_type": "TempBasal",
      "temp": "absolute",
      "_description": "TempBasal 2016-07-08T01:51:03 head[2], body[1] op[0x33]",
      "timestamp": "2016-07-08T01:51:03-04:00",
      "_body": "00",
      "_head": "3300",
      "rate": 0,
      "_date": "43f3014810"
    },
    "eventType": "Temp Basal",
    "medtronic": "mm://openaps/mm-format-ns-treatments/Temp Basal",
    "created_at": "2016-07-08T01:51:03-04:00",
    "enteredBy": "openaps://medtronic/722"
  },
  {
    "duration": "30",
    "raw_duration": {
      "_type": "TempBasalDuration",
      "_description": "TempBasalDuration 2016-07-08T01:31:05 head[2], body[0] op[0x16]",
      "timestamp": "2016-07-08T01:31:05-04:00",
      "_body": "",
      "_head": "1601",
      "duration (min)": 30,
      "_date": "45df014810"
    },
    "timestamp": "2016-07-08T01:31:05-04:00",
    "absolute": "0",
    "rate": 0,
    "raw_rate": {
      "_type": "TempBasal",
      "temp": "absolute",
      "_description": "TempBasal 2016-07-08T01:31:05 head[2], body[1] op[0x33]",
      "timestamp": "2016-07-08T01:31:05-04:00",
      "_body": "00",
      "_head": "3300",
      "rate": 0,
      "_date": "45df014810"
    },
    "eventType": "Temp Basal",
    "medtronic": "mm://openaps/mm-format-ns-treatments/Temp Basal",
    "created_at": "2016-07-08T01:31:05-04:00",
    "enteredBy": "openaps://medtronic/722"
  },
  {
    "duration": "30",
    "raw_duration": {
      "_type": "TempBasalDuration",
      "_description": "TempBasalDuration 2016-07-08T01:26:05 head[2], body[0] op[0x16]",
      "timestamp": "2016-07-08T01:26:05-04:00",
      "_body": "",
      "_head": "1601",
      "duration (min)": 30,
      "_date": "45da014810"
    },
    "timestamp": "2016-07-08T01:26:05-04:00",
    "absolute": "1.1",
    "rate": 1.1,
    "raw_rate": {
      "_type": "TempBasal",
      "temp": "absolute",
      "_description": "TempBasal 2016-07-08T01:26:05 head[2], body[1] op[0x33]",
      "timestamp": "2016-07-08T01:26:05-04:00",
      "_body": "00",
      "_head": "332c",
      "rate": 1.1,
      "_date": "45da014810"
    },
    "eventType": "Temp Basal",
    "medtronic": "mm://openaps/mm-format-ns-treatments/Temp Basal",
    "created_at": "2016-07-08T01:26:05-04:00",
    "enteredBy": "openaps://medtronic/722"
  },
  {
    "duration": "30",
    "raw_duration": {
      "_type": "TempBasalDuration",
      "_description": "TempBasalDuration 2016-07-08T01:21:04 head[2], body[0] op[0x16]",
      "timestamp": "2016-07-08T01:21:04-04:00",
      "_body": "",
      "_head": "1601",
      "duration (min)": 30,
      "_date": "44d5014810"
    },
    "timestamp": "2016-07-08T01:21:04-04:00",
    "absolute": "0.2",
    "rate": 0.2,
    "raw_rate": {
      "_type": "TempBasal",
      "temp": "absolute",
      "_description": "TempBasal 2016-07-08T01:21:04 head[2], body[1] op[0x33]",
      "timestamp": "2016-07-08T01:21:04-04:00",
      "_body": "00",
      "_head": "3308",
      "rate": 0.2,
      "_date": "44d5014810"
    },
    "eventType": "Temp Basal",
    "medtronic": "mm://openaps/mm-format-ns-treatments/Temp Basal",
    "created_at": "2016-07-08T01:21:04-04:00",
    "enteredBy": "openaps://medtronic/722"
  },
  {
    "duration": "30",
    "raw_duration": {
      "_type": "TempBasalDuration",
      "_description": "TempBasalDuration 2016-07-08T01:16:00 head[2], body[0] op[0x16]",
      "timestamp": "2016-07-08T01:16:00-04:00",
      "_body": "",
      "_head": "1601",
      "duration (min)": 30,
      "_date": "40d0014810"
    },
    "timestamp": "2016-07-08T01:16:00-04:00",
    "absolute": "1.1",
    "rate": 1.1,
    "raw_rate": {
      "_type": "TempBasal",
      "temp": "absolute",
      "_description": "TempBasal 2016-07-08T01:16:00 head[2], body[1] op[0x33]",
      "timestamp": "2016-07-08T01:16:00-04:00",
      "_body": "00",
      "_head": "332c",
      "rate": 1.1,
      "_date": "40d0014810"
    },
    "eventType": "Temp Basal",
    "medtronic": "mm://openaps/mm-format-ns-treatments/Temp Basal",
    "created_at": "2016-07-08T01:16:00-04:00",
    "enteredBy": "openaps://medtronic/722"
  },
  {
    "duration": "30",
    "raw_duration": {
      "_type": "TempBasalDuration",
      "_description": "TempBasalDuration 2016-07-08T01:11:03 head[2], body[0] op[0x16]",
      "timestamp": "2016-07-08T01:11:03-04:00",
      "_body": "",
      "_head": "1601",
      "duration (min)": 30,
      "_date": "43cb014810"
    },
    "timestamp": "2016-07-08T01:11:03-04:00",
    "absolute": "0",
    "rate": 0,
    "raw_rate": {
      "_type": "TempBasal",
      "temp": "absolute",
      "_description": "TempBasal 2016-07-08T01:11:03 head[2], body[1] op[0x33]",
      "timestamp": "2016-07-08T01:11:03-04:00",
      "_body": "00",
      "_head": "3300",
      "rate": 0,
      "_date": "43cb014810"
    },
    "eventType": "Temp Basal",
    "medtronic": "mm://openaps/mm-format-ns-treatments/Temp Basal",
    "created_at": "2016-07-08T01:11:03-04:00",
    "enteredBy": "openaps://medtronic/722"
  },
  {
    "duration": "30",
    "raw_duration": {
      "_type": "TempBasalDuration",
      "_description": "TempBasalDuration 2016-07-08T00:55:59 head[2], body[0] op[0x16]",
      "timestamp": "2016-07-08T00:55:59-04:00",
      "_body": "",
      "_head": "1601",
      "duration (min)": 30,
      "_date": "7bf7004810"
    },
    "timestamp": "2016-07-08T00:55:59-04:00",
    "absolute": "0",
    "rate": 0,
    "raw_rate": {
      "_type": "TempBasal",
      "temp": "absolute",
      "_description": "TempBasal 2016-07-08T00:55:59 head[2], body[1] op[0x33]",
      "timestamp": "2016-07-08T00:55:59-04:00",
      "_body": "00",
      "_head": "3300",
      "rate": 0,
      "_date": "7bf7004810"
    },
    "eventType": "Temp Basal",
    "medtronic": "mm://openaps/mm-format-ns-treatments/Temp Basal",
    "created_at": "2016-07-08T00:55:59-04:00",
    "enteredBy": "openaps://medtronic/722"
  },
  {
    "duration": "30",
    "raw_duration": {
      "_type": "TempBasalDuration",
      "_description": "TempBasalDuration 2016-07-08T00:41:04 head[2], body[0] op[0x16]",
      "timestamp": "2016-07-08T00:41:04-04:00",
      "_body": "",
      "_head": "1601",
      "duration (min)": 30,
      "_date": "44e9004810"
    },
    "timestamp": "2016-07-08T00:41:04-04:00",
    "absolute": "0",
    "rate": 0,
    "raw_rate": {
      "_type": "TempBasal",
      "temp": "absolute",
      "_description": "TempBasal 2016-07-08T00:41:04 head[2], body[1] op[0x33]",
      "timestamp": "2016-07-08T00:41:04-04:00",
      "_body": "00",
      "_head": "3300",
      "rate": 0,
      "_date": "44e9004810"
    },
    "eventType": "Temp Basal",
    "medtronic": "mm://openaps/mm-format-ns-treatments/Temp Basal",
    "created_at": "2016-07-08T00:41:04-04:00",
    "enteredBy": "openaps://medtronic/722"
  },
  {
    "duration": "30",
    "raw_duration": {
      "_type": "TempBasalDuration",
      "_description": "TempBasalDuration 2016-07-08T00:26:00 head[2], body[0] op[0x16]",
      "timestamp": "2016-07-08T00:26:00-04:00",
      "_body": "",
      "_head": "1601",
      "duration (min)": 30,
      "_date": "40da004810"
    },
    "timestamp": "2016-07-08T00:26:00-04:00",
    "absolute": "0",
    "rate": 0,
    "raw_rate": {
      "_type": "TempBasal",
      "temp": "absolute",
      "_description": "TempBasal 2016-07-08T00:26:00 head[2], body[1] op[0x33]",
      "timestamp": "2016-07-08T00:26:00-04:00",
      "_body": "00",
      "_head": "3300",
      "rate": 0,
      "_date": "40da004810"
    },
    "eventType": "Temp Basal",
    "medtronic": "mm://openaps/mm-format-ns-treatments/Temp Basal",
    "created_at": "2016-07-08T00:26:00-04:00",
    "enteredBy": "openaps://medtronic/722"
  },
  {
    "duration": "30",
    "raw_duration": {
      "_type": "TempBasalDuration",
      "_description": "TempBasalDuration 2016-07-08T00:21:03 head[2], body[0] op[0x16]",
      "timestamp": "2016-07-08T00:21:03-04:00",
      "_body": "",
      "_head": "1601",
      "duration (min)": 30,
      "_date": "43d5004810"
    },
    "timestamp": "2016-07-08T00:21:03-04:00",
    "absolute": "1.1",
    "rate": 1.1,
    "raw_rate": {
      "_type": "TempBasal",
      "temp": "absolute",
      "_description": "TempBasal 2016-07-08T00:21:03 head[2], body[1] op[0x33]",
      "timestamp": "2016-07-08T00:21:03-04:00",
      "_body": "00",
      "_head": "332c",
      "rate": 1.1,
      "_date": "43d5004810"
    },
    "eventType": "Temp Basal",
    "medtronic": "mm://openaps/mm-format-ns-treatments/Temp Basal",
    "created_at": "2016-07-08T00:21:03-04:00",
    "enteredBy": "openaps://medtronic/722"
  },
  {
    "duration": "30",
    "raw_duration": {
      "_type": "TempBasalDuration",
      "_description": "TempBasalDuration 2016-07-07T23:56:00 head[2], body[0] op[0x16]",
      "timestamp": "2016-07-07T23:56:00-04:00",
      "_body": "",
      "_head": "1601",
      "duration (min)": 30,
      "_date": "40f8174710"
    },
    "timestamp": "2016-07-07T23:56:00-04:00",
    "absolute": "0",
    "rate": 0,
    "raw_rate": {
      "_type": "TempBasal",
      "temp": "absolute",
      "_description": "TempBasal 2016-07-07T23:56:00 head[2], body[1] op[0x33]",
      "timestamp": "2016-07-07T23:56:00-04:00",
      "_body": "00",
      "_head": "3300",
      "rate": 0,
      "_date": "40f8174710"
    },
    "eventType": "Temp Basal",
    "medtronic": "mm://openaps/mm-format-ns-treatments/Temp Basal",
    "created_at": "2016-07-07T23:56:00-04:00",
    "enteredBy": "openaps://medtronic/722"
  },
  {
    "duration": "30",
    "raw_duration": {
      "_type": "TempBasalDuration",
      "_description": "TempBasalDuration 2016-07-07T23:41:09 head[2], body[0] op[0x16]",
      "timestamp": "2016-07-07T23:41:09-04:00",
      "_body": "",
      "_head": "1601",
      "duration (min)": 30,
      "_date": "49e9174710"
    },
    "timestamp": "2016-07-07T23:41:09-04:00",
    "absolute": "0",
    "rate": 0,
    "raw_rate": {
      "_type": "TempBasal",
      "temp": "absolute",
      "_description": "TempBasal 2016-07-07T23:41:09 head[2], body[1] op[0x33]",
      "timestamp": "2016-07-07T23:41:09-04:00",
      "_body": "00",
      "_head": "3300",
      "rate": 0,
      "_date": "49e9174710"
    },
    "eventType": "Temp Basal",
    "medtronic": "mm://openaps/mm-format-ns-treatments/Temp Basal",
    "created_at": "2016-07-07T23:41:09-04:00",
    "enteredBy": "openaps://medtronic/722"
  }
]
