[
  {
    "direction": "Flat", 
    "noise": 1, 
    "delta": -1.461, 
    "dateString": "2016-07-16T17:03:45.819-0400", 
    "sgv": 105, 
    "date": 1468703025819, 
    "unfiltered": 131776, 
    "rssi": 100, 
    "device": "xDrip-WifiWixel", 
    "filtered": 133664, 
    "_id": "578aa1b761745ce99c686d41", 
    "type": "sgv", 
    "glucose": 105
  }, 
  {
    "direction": "Flat", 
    "noise": 1, 
    "delta": -0.586, 
    "dateString": "2016-07-16T16:58:47.824-0400", 
    "sgv": 106, 
    "date": 1468702727824, 
    "unfiltered": 133120, 
    "rssi": 100, 
    "device": "xDrip-WifiWixel", 
    "filtered": 134240, 
    "_id": "578aa1b561745ce99c686d40", 
    "type": "sgv", 
    "glucose": 106
  }, 
  {
    "direction": "Flat", 
    "trend": 4, 
    "dateString": "2016-07-16T20:58:43.000Z", 
    "sgv": 97, 
    "device": "share2", 
    "date": 1468702723000, 
    "_id": "578aa07c61745ce99c686d15", 
    "type": "sgv", 
    "glucose": 97
  }, 
  {
    "direction": "Flat", 
    "noise": 1, 
    "delta": -0.225, 
    "dateString": "2016-07-16T16:53:46.824-0400", 
    "sgv": 107, 
    "date": 1468702426824, 
    "unfiltered": 133664, 
    "rssi": 100, 
    "device": "xDrip-WifiWixel", 
    "filtered": 134272, 
    "_id": "578aa1b261745ce99c686d3f", 
    "type": "sgv", 
    "glucose": 107
  }, 
  {
    "direction": "Flat", 
    "trend": 4, 
    "dateString": "2016-07-16T20:53:43.000Z", 
    "sgv": 98, 
    "device": "share2", 
    "date": 1468702423000, 
    "_id": "578a9f5061745ce99c686d02", 
    "type": "sgv", 
    "glucose": 98
  }, 
  {
    "direction": "Flat", 
    "trend": 4, 
    "dateString": "2016-07-16T20:48:43.000Z", 
    "sgv": 100, 
    "device": "share2", 
    "date": 1468702123000, 
    "_id": "578a9e2461745ce99c686ce3", 
    "type": "sgv", 
    "glucose": 100
  }, 
  {
    "direction": "Flat", 
    "noise": 1, 
    "delta": 0.069, 
    "dateString": "2016-07-16T16:43:47.825-0400", 
    "sgv": 107, 
    "date": 1468701827825, 
    "unfiltered": 134080, 
    "rssi": 100, 
    "device": "xDrip-WifiWixel", 
    "filtered": 133728, 
    "_id": "578aa1b061745ce99c686d3e", 
    "type": "sgv", 
    "glucose": 107
  }, 
  {
    "direction": "Flat", 
    "trend": 4, 
    "dateString": "2016-07-16T20:43:43.000Z", 
    "sgv": 99, 
    "device": "share2", 
    "date": 1468701823000, 
    "_id": "578a9cf861745ce99c686cca", 
    "type": "sgv", 
    "glucose": 99
  }, 
  {
    "direction": "Flat", 
    "noise": 1, 
    "delta": 0.379, 
    "dateString": "2016-07-16T16:38:47.826-0400", 
    "sgv": 107, 
    "date": 1468701527826, 
    "unfiltered": 134016, 
    "rssi": 100, 
    "device": "xDrip-WifiWixel", 
    "filtered": 133536, 
    "_id": "578aa1ae61745ce99c686d3d", 
    "type": "sgv", 
    "glucose": 107
  }, 
  {
    "direction": "Flat", 
    "trend": 4, 
    "dateString": "2016-07-16T20:38:43.000Z", 
    "sgv": 99, 
    "device": "share2", 
    "date": 1468701523000, 
    "_id": "578a9bcc61745ce99c686cb5", 
    "type": "sgv", 
    "glucose": 99
  }
]